topsis/__init__.py
topsis/topsis.py
topsis_madhavdembla_102303609-1.0.0.dist-info/METADATA
topsis_madhavdembla_102303609-1.0.0.dist-info/WHEEL
topsis_madhavdembla_102303609-1.0.0.dist-info/entry_points.txt
topsis_madhavdembla_102303609-1.0.0.dist-info/top_level.txt
topsis_madhavdembla_102303609-1.0.0.dist-info/RECORD
