Metadata-Version: 2.1
Name: topsis-madhavdembla-102303609
Version: 1.0.0
Summary: TOPSIS implementation using Python
Author: Madhav Dembla
Requires-Dist: pandas
Requires-Dist: numpy
